macocr_cli/__init__.py
macocr_cli/__main__.py
macocr_cli/utils.py
mac_ocr_cli-0.2.9.dist-info/LICENSE
mac_ocr_cli-0.2.9.dist-info/METADATA
mac_ocr_cli-0.2.9.dist-info/WHEEL
mac_ocr_cli-0.2.9.dist-info/entry_points.txt
mac_ocr_cli-0.2.9.dist-info/top_level.txt
mac_ocr_cli-0.2.9.dist-info/RECORD
